moban_handlebars/__init__.py
moban_handlebars/_version.py
moban_handlebars/api.py
moban_handlebars/constants.py
moban_handlebars/engine.py
moban_handlebars-0.0.5.dist-info/LICENSE
moban_handlebars-0.0.5.dist-info/METADATA
moban_handlebars-0.0.5.dist-info/WHEEL
moban_handlebars-0.0.5.dist-info/top_level.txt
moban_handlebars-0.0.5.dist-info/RECORD
