Metadata-Version: 2.1
Name: moban-handlebars
Version: 0.0.5
Summary: Provide handlebars templating capability to moban.
Home-page: https://github.com/moremoban/moban-handlebars
Author: Charlie Liu, C.W. et al
Author-email: wangc_2011@hotmail.com
License: MIT
Download-URL: https://github.com/moremoban/moban-handlebars/archive/0.0.5.tar.gz
Keywords: python
Platform: UNKNOWN
Classifier: Topic :: Software Development :: Libraries
Classifier: Programming Language :: Python
Classifier: Intended Audience :: Developers
Classifier: Programming Language :: Python :: 2.6
Classifier: Programming Language :: Python :: 2.7
Classifier: Programming Language :: Python :: 3.3
Classifier: Programming Language :: Python :: 3.4
Classifier: Programming Language :: Python :: 3.5
Classifier: Programming Language :: Python :: 3.6
Classifier: Programming Language :: Python :: 3.7
Classifier: Programming Language :: Python :: 3.8
Requires-Dist: pybars3
Requires-Dist: lml (>=0.0.9)
